sgnl/__init__.py
sgnl/_version.py
sgnl/cbc_template_fir.py
sgnl/chirptime.py
sgnl/control.py
sgnl/events.py
sgnl/gracedb.py
sgnl/kernels.py
sgnl/measure_psd.py
sgnl/psd.py
sgnl/py.typed
sgnl/sgnlio.py
sgnl/simulation.py
sgnl/sort_bank.py
sgnl/spawaveform.py
sgnl/strike_object.py
sgnl/svd_bank.py
sgnl/templates.py
sgnl/utils.py
sgnl/viz.py
sgnl/bin/__init__.py
sgnl/bin/add_segments.py
sgnl/bin/assign_far.py
sgnl/bin/assign_likelihood.py
sgnl/bin/create_prior_diststats.py
sgnl/bin/dagger.py
sgnl/bin/extinct_bin.py
sgnl/bin/flopulator.py
sgnl/bin/inspiral.py
sgnl/bin/inspiral_bank_splitter.py
sgnl/bin/inspiral_set_svdbin_option.py
sgnl/bin/inspiral_svd_bank.py
sgnl/bin/ll_dagger.py
sgnl/bin/ll_dq.py
sgnl/bin/ll_inspiral_event_plotter.py
sgnl/bin/ll_inspiral_event_uploader.py
sgnl/bin/ll_marginalize_likelihoods_online.py
sgnl/bin/ll_pastro_uploader.py
sgnl/bin/ll_remove_counts.py
sgnl/bin/ll_set_gracedb_far_threshold.py
sgnl/bin/ll_trigger_counter.py
sgnl/bin/median_of_psds.py
sgnl/bin/plot_psd.py
sgnl/bin/query_segments.py
sgnl/bin/reference_psd.py
sgnl/bin/results_page.py
sgnl/bin/segment_ops.py
sgnl/bin/sim_page.py
sgnl/dags/__init__.py
sgnl/dags/config.py
sgnl/dags/default_config.yml
sgnl/dags/layers.py
sgnl/dags/segments.py
sgnl/dags/util.py
sgnl/plots/psd.py
sgnl/plots/util.py
sgnl/sinks/__init__.py
sgnl/sinks/gracedb_sink.py
sgnl/sinks/impulse.py
sgnl/sinks/psd_sink.py
sgnl/sinks/stillsuit_sink.py
sgnl/sinks/strike_sink.py
sgnl/transforms/__init__.py
sgnl/transforms/eye_candy.py
sgnl/transforms/horizon.py
sgnl/transforms/itacacac.py
sgnl/transforms/lloid.py
sgnl/transforms/lloid_correlate.py
sgnl/transforms/strike.py
sgnl-0.1.1.dist-info/METADATA
sgnl-0.1.1.dist-info/WHEEL
sgnl-0.1.1.dist-info/entry_points.txt
sgnl-0.1.1.dist-info/top_level.txt
sgnl-0.1.1.dist-info/RECORD
