Metadata-Version: 2.4
Name: sgnl
Version: 0.1.1
Summary: Inspiral Search Pipeline using SGN Framework
Author-email: Chad Hanna <crh184@psu.edu>, Yun-Jing Huang <yzh5436@psu.edu>, James Kennington <jmk7376@psu.edu>
License: MPL-2.0
Project-URL: Homepage, https://git.ligo.org/greg/sgnl
Project-URL: Documentation, https://docs.ligo.org/greg/sgnl
Project-URL: Issues, https://git.ligo.org/greg/sgnl/issues
Classifier: Programming Language :: Python :: 3
Classifier: License :: OSI Approved :: Mozilla Public License 2.0 (MPL 2.0)
Classifier: Operating System :: OS Independent
Requires-Python: >=3.11
Requires-Dist: pandas
Requires-Dist: ligo-gracedb==2.14.1
Requires-Dist: lalsuite>=7.26
Requires-Dist: igwn-ligolw>=2.1.0
Requires-Dist: igwn-segments
Requires-Dist: sgn
Requires-Dist: sgn-ts
Requires-Dist: sgn-ligo
Requires-Dist: gw-strike
Requires-Dist: flask
Requires-Dist: ligo-scald
Provides-Extra: test
Requires-Dist: pytest; extra == "test"
Requires-Dist: pytest-cov; extra == "test"
Requires-Dist: lalsuite; extra == "test"
Requires-Dist: torch<=2.5.1; extra == "test"
Requires-Dist: gwpy; extra == "test"
Provides-Extra: docs
Requires-Dist: mkdocs; extra == "docs"
Requires-Dist: mkdocstrings; extra == "docs"
Requires-Dist: mkdocstrings-python; extra == "docs"
Requires-Dist: mkdocs-material; extra == "docs"
Requires-Dist: pymdown-extensions; extra == "docs"
Requires-Dist: mkdocs-autorefs<1.3.0; extra == "docs"
Provides-Extra: lint
Requires-Dist: black; extra == "lint"
Requires-Dist: flake8; extra == "lint"
Requires-Dist: flake8-bandit; extra == "lint"
Requires-Dist: flake8-black; extra == "lint"
Requires-Dist: flake8-bugbear; extra == "lint"
Requires-Dist: flake8-future-annotations; extra == "lint"
Requires-Dist: flake8-isort; extra == "lint"
Requires-Dist: flake8-logging-format; extra == "lint"
Requires-Dist: flake8-pyproject; extra == "lint"
Requires-Dist: isort; extra == "lint"
Requires-Dist: mypy; extra == "lint"
Requires-Dist: mypy-extensions; extra == "lint"
Requires-Dist: types-requests; extra == "lint"
Requires-Dist: types-PyYAML; extra == "lint"
Provides-Extra: dev
Requires-Dist: sgnl[docs]; extra == "dev"
Requires-Dist: sgnl[lint]; extra == "dev"
Requires-Dist: sgnl[test]; extra == "dev"
Provides-Extra: dag
Requires-Dist: ezdag; extra == "dag"
